migrations/__init__.py
django_geodata-0.1.1.dist-info/LICENSE
django_geodata-0.1.1.dist-info/METADATA
django_geodata-0.1.1.dist-info/WHEEL
django_geodata-0.1.1.dist-info/top_level.txt
django_geodata-0.1.1.dist-info/RECORD
