Metadata-Version: 2.1
Name: django-geodata
Version: 0.1.1
Summary: Django app to add GEO data [Countries, Cities, Time Zones, Geo Points and their Polygons in geoJSON format.]
Home-page: https://github.com/udartsev/django-geodata
Author: Vladimir Udartsev
Author-email: v.udartsev@gmail.com
License: MIT License
Platform: UNKNOWN
Classifier: Environment :: Web Environment
Classifier: Framework :: Django
Classifier: Framework :: Django :: 2.2
Classifier: Intended Audience :: Developers
Classifier: License :: Aladdin Free Public License (AFPL)
Classifier: Operating System :: OS Independent
Classifier: Programming Language :: Python
Classifier: Programming Language :: Python :: 3.5
Classifier: Programming Language :: Python :: 3.6
Classifier: Programming Language :: Python :: 3.7
Classifier: Topic :: Internet :: WWW/HTTP
Classifier: Topic :: Internet :: WWW/HTTP :: Dynamic Content
Classifier: Topic :: Database
